quantybt/__init__.py
quantybt/analyzer.py
quantybt/montecarlo.py
quantybt/optimizer.py
quantybt/plots.py
quantybt/sensitivity.py
quantybt/stats.py
quantybt/strategy.py
quantybt/utils.py
quantybt/data/__init__.py
quantybt/data/loader.py
quantybt/models/__init__.py
quantybt/models/filter.py
quantybt-0.1.13.dist-info/licenses/LICENSE-txt
quantybt-0.1.13.dist-info/METADATA
quantybt-0.1.13.dist-info/WHEEL
quantybt-0.1.13.dist-info/top_level.txt
quantybt-0.1.13.dist-info/RECORD
