Metadata-Version: 2.4
Name: quantybt
Version: 0.1.13
Summary: lightweight backtesting framework with in-built advanced statistical backtesting methods and custom models
Author-email: Niklas <niklasschluetter.business@gmail.com>
License: MIT
Classifier: Programming Language :: Python :: 3
Classifier: License :: OSI Approved :: MIT License
Classifier: Operating System :: OS Independent
Requires-Python: >=3.8
License-File: LICENSE-txt
Requires-Dist: pandas
Requires-Dist: numpy
Requires-Dist: scipy
Requires-Dist: plotly
Requires-Dist: kaleido
Requires-Dist: vectorbt
Requires-Dist: holoviews
Requires-Dist: hyperopt
Requires-Dist: ccxt
Requires-Dist: pyarrow
Dynamic: license-file
